UniversEncrypt/__init__.py
UniversEncrypt/main.py
UniversEncrypt-0.0.1.dist-info/LICENSE
UniversEncrypt-0.0.1.dist-info/METADATA
UniversEncrypt-0.0.1.dist-info/WHEEL
UniversEncrypt-0.0.1.dist-info/top_level.txt
UniversEncrypt-0.0.1.dist-info/RECORD
