Metadata-Version: 2.1
Name: UniversEncrypt
Version: 0.0.1
Summary: This is Best encrypt in the world!
Home-page: UNKNOWN
Author: IvanIvanov
Author-email: ivanko@gmail.com
License: UNKNOWN
Platform: UNKNOWN
Classifier: Programming Language :: Python :: 3.8
Classifier: License :: OSI Approved :: MIT License
Classifier: Operating System :: OS Independent
Requires-Python: >=3.6
License-File: LICENSE
